odoo/addons/l10n_es_payment_order_confirming_aef/README.rst
odoo/addons/l10n_es_payment_order_confirming_aef/__init__.py
odoo/addons/l10n_es_payment_order_confirming_aef/__manifest__.py
odoo/addons/l10n_es_payment_order_confirming_aef/data/account_payment_method.xml
odoo/addons/l10n_es_payment_order_confirming_aef/i18n/es.po
odoo/addons/l10n_es_payment_order_confirming_aef/i18n/l10n_es_payment_order_confirming_aef.pot
odoo/addons/l10n_es_payment_order_confirming_aef/models/__init__.py
odoo/addons/l10n_es_payment_order_confirming_aef/models/account_payment_method.py
odoo/addons/l10n_es_payment_order_confirming_aef/models/account_payment_mode.py
odoo/addons/l10n_es_payment_order_confirming_aef/models/account_payment_order.py
odoo/addons/l10n_es_payment_order_confirming_aef/models/confirming_aef.py
odoo/addons/l10n_es_payment_order_confirming_aef/readme/CONFIGURE.md
odoo/addons/l10n_es_payment_order_confirming_aef/readme/CONTRIBUTORS.md
odoo/addons/l10n_es_payment_order_confirming_aef/readme/DESCRIPTION.md
odoo/addons/l10n_es_payment_order_confirming_aef/readme/USAGE.md
odoo/addons/l10n_es_payment_order_confirming_aef/static/description/icon.png
odoo/addons/l10n_es_payment_order_confirming_aef/static/description/index.html
odoo/addons/l10n_es_payment_order_confirming_aef/tests/__init__.py
odoo/addons/l10n_es_payment_order_confirming_aef/tests/test_payment_order_confirming_aef.py
odoo/addons/l10n_es_payment_order_confirming_aef/views/account_payment_mode_view.xml
odoo_addon_l10n_es_payment_order_confirming_aef-18.0.1.0.2.dist-info/METADATA
odoo_addon_l10n_es_payment_order_confirming_aef-18.0.1.0.2.dist-info/WHEEL
odoo_addon_l10n_es_payment_order_confirming_aef-18.0.1.0.2.dist-info/top_level.txt
odoo_addon_l10n_es_payment_order_confirming_aef-18.0.1.0.2.dist-info/RECORD
